clustipy/__init__.py
clustipy/utils.py
clustipy/cmd/__init__.py
clustipy/cmd/clustipy.py
tests/__init__.py
tests/test_clustipy.py
tests/utils.py
ClustIPy-0.1.0.dist-info/LICENSE
ClustIPy-0.1.0.dist-info/METADATA
ClustIPy-0.1.0.dist-info/WHEEL
ClustIPy-0.1.0.dist-info/entry_points.txt
ClustIPy-0.1.0.dist-info/top_level.txt
ClustIPy-0.1.0.dist-info/RECORD
