Metadata-Version: 2.1
Name: ClustIPy
Version: 0.1.0
Summary: Clustering IPs
Home-page: https://github.com/shuichiro-makigaki/ClustIPy
Author: Shuichiro MAKIGAKI
Author-email: shuichiro.makigaki@gmail.com
License: MIT
Platform: UNKNOWN
